esg/__init__.py
esg/__main__.py
esg/_types.py
esg/config.py
esg/importer.py
esg/logging.py
esg/main.py
esg/server.py
esg/subprocess.py
esg/workers.py
esg/_handlers/__init__.py
esg/_handlers/http.py
esg/lifespan/__init__.py
esg/lifespan/off.py
esg/lifespan/on.py
esg/loops/__init__.py
esg/loops/asyncio.py
esg/loops/auto.py
esg/loops/uvloop.py
esg/middleware/__init__.py
esg/middleware/asgi2.py
esg/middleware/debug.py
esg/middleware/message_logger.py
esg/middleware/proxy_headers.py
esg/middleware/wsgi.py
esg/protocols/__init__.py
esg/protocols/utils.py
esg/protocols/http/__init__.py
esg/protocols/http/auto.py
esg/protocols/http/errors.py
esg/protocols/http/flow_control.c
esg/protocols/http/flow_control.cpython-310-darwin.so
esg/protocols/http/protocol.c
esg/protocols/http/protocol.cpython-310-darwin.so
esg/protocols/websockets/__init__.py
esg/protocols/websockets/auto.py
esg/protocols/websockets/websockets_impl.py
esg/protocols/websockets/wsproto_impl.py
esg/supervisors/__init__.py
esg/supervisors/basereload.py
esg/supervisors/multiprocess.py
esg/supervisors/statreload.py
esg/supervisors/watchgodreload.py
esg-0.2.0.dist-info/LICENSE.md
esg-0.2.0.dist-info/METADATA
esg-0.2.0.dist-info/WHEEL
esg-0.2.0.dist-info/entry_points.txt
esg-0.2.0.dist-info/top_level.txt
esg-0.2.0.dist-info/RECORD
