Metadata-Version: 2.1
Name: esg
Version: 0.2.0
Summary: Enhanced Service Gateway
Home-page: https://github.com/mtag-dev/esg
Author: Stanislav Dubrovskyi
Author-email: s.dubrovskyi@cleverdec.com
License: BSD
Project-URL: Source, https://github.com/mtag-dev/esg
Project-URL: Changelog, https://github.com/mtag-dev/esg/blob/master/CHANGELOG.md
Platform: UNKNOWN
Classifier: Intended Audience :: Developers
Classifier: Intended Audience :: System Administrators
Classifier: Operating System :: POSIX
Classifier: Operating System :: MacOS :: MacOS X
Classifier: Development Status :: 4 - Beta
Classifier: Environment :: Web Environment
Classifier: License :: OSI Approved :: BSD License
Classifier: Topic :: Internet
Classifier: Topic :: Internet :: WWW/HTTP
Classifier: Topic :: Internet :: WWW/HTTP :: HTTP Servers
Classifier: Topic :: Software Development :: Libraries :: Application Frameworks
Classifier: Topic :: Software Development :: Libraries :: Python Modules
Classifier: Topic :: Software Development :: Libraries
Classifier: Topic :: Software Development
Classifier: Programming Language :: Python
Classifier: Programming Language :: Python :: 3
Classifier: Programming Language :: Python :: 3 :: Only
Classifier: Programming Language :: Python :: 3.9
Classifier: Programming Language :: Python :: 3.10
Classifier: Programming Language :: Python :: Implementation :: CPython
Classifier: Framework :: AsyncIO
License-File: LICENSE.md
Requires-Dist: asgiref (>=3.4.0)
Requires-Dist: click (>=7.0)
Requires-Dist: h11 (>=0.8)
Requires-Dist: Cython (<0.30.0,>=0.29.24)
Provides-Extra: standard
Requires-Dist: websockets (>=10.0) ; extra == 'standard'
Requires-Dist: watchgod (>=0.6) ; extra == 'standard'
Requires-Dist: python-dotenv (>=0.13) ; extra == 'standard'
Requires-Dist: PyYAML (>=5.1) ; extra == 'standard'
Requires-Dist: uvloop (!=0.15.0,!=0.15.1,>=0.14.0) ; (sys_platform != "win32" and (sys_platform != "cygwin" and platform_python_implementation != "PyPy")) and extra == 'standard'
Requires-Dist: colorama (>=0.4) ; (sys_platform == "win32") and extra == 'standard'
Provides-Extra: test
Requires-Dist: Cython (<0.30.0,>=0.29.24) ; extra == 'test'
